{
  "n_chapters": 24,
  "n_perm_articles": 151,
  "n_perm_fracciones": 345,
  "n_trans_caps": 1,
  "n_trans_articles": 10,
  "n_trans_fracciones": 0,
  "chapter_labels": [
    "CAPÍTULO ÚNICO",
    "CAPÍTULO I ESTRUCTURA DEL SISTEMA ESTATAL DE COMPRAS GUBERNAMENTALES, ENAJENACIONES Y CONTRATACIÓN DE SERVICIOS",
    "CAPÍTULO II SISTEMA ELECTRÓNICO DE COMPRAS GUBERNAMENTALES Y CONTRATACIÓN DE OBRA PÚBLICA",
    "CAPÍTULO III REGISTRO ESTATAL ÚNICO DE PROVEEDORES Y CONTRATISTAS",
    "CAPÍTULO IV COMITÉS DE ADQUISICIONES DE LOS ENTES PÚBLICOS",
    "CAPÍTULO V UNIDADES CENTRALIZADAS DE COMPRAS",
    "CAPÍTULO VI TESTIGOS SOCIALES",
    "CAPÍTULO I",
    "SECCIÓN PRIMERA DISPOSICIONES GENERALES",
    "SECCIÓN SEGUNDA PROCEDIMIENTOS DE LICITACIÓN PÚBLICA",
    "SECCIÓN TERCERA EXCEPCIONES A LA LICITACIÓN PÚBLICA",
    "CAPÍTULO III CONTRATOS",
    "CAPÍTULO IV INCONFORMIDADES",
    "CAPÍTULO V PROCEDIMIENTO DE CONCILIACIÓN",
    "CAPÍTULO VI INFORMACIÓN Y VERIFICACIÓN",
    "CAPÍTULO VII SANCIONES",
    "TÍTULO CUARTO PROTOCOLO DE ACTUACIÓN DE LOS SERVIDORES PÚBLICOS EN MATERIA DE CONTRATACIONES PÚBLICAS",
    "CAPÍTULO I ARRENDAMIENTOS DE BIENES INMUEBLES",
    "CAPÍTULO II ADQUISICIONES DE BIENES INMUEBLES",
    "CAPÍTULO I ALMACENES",
    "CAPÍTULO II ENAJENACIONES",
    "CAPÍTULO I OBJETO Y PATRIMONIO",
    "CAPÍTULO II INTEGRACIÓN Y ATRIBUCIONES",
    "CAPÍTULO III APORTACIÓN CINCO AL MILLAR"
  ],
  "chapter_kind_breakdown": {
    "CAPÍTULO": 20,
    "SECCIÓN": 3,
    "TÍTULO": 1
  }
}