{
  "n_chapters": 37,
  "n_perm_articles": 112,
  "n_perm_fracciones": 271,
  "n_trans_caps": 1,
  "n_trans_articles": 6,
  "n_trans_fracciones": 1,
  "chapter_labels": [
    "CAPÍTULO UNICO DE LA RECEPCION DE LOS INGRESOS Y DEFINICIONES",
    "CAPÍTULO PRIMERO DEL IMPUESTO PREDIAL",
    "CAPÍTULO SEGUNDO DEL IMPUESTO SOBRE TRANSMISIONES PATRIMONIALES",
    "CAPÍTULO TERCERO DEL IMPUESTO SOBRE NEGOCIOS JURÍDICOS",
    "CAPÍTULO CUARTO DEL IMPUESTO SOBRE ESPECTÁCULOS PÚBLICOS",
    "CAPÍTULO QUINTO DE LOS IMPUESTOS EXTRAORDINARIOS",
    "CAPÍTULO SEXTO ACCESORIOS DE LOS IMPUESTOS",
    "CAPÍTULO ÚNICO DE LAS CONTRIBUCIONES DE MEJORAS POR OBRAS PÚBLICAS",
    "CAPÍTULO PRIMERO DEL USO DE PISO",
    "CAPÍTULO SEGUNDO DE LOS ESTACIONAMIENTOS",
    "CAPÍTULO TERCERO DEL USO, GOCE, APROVECHAMIENTOS O EXPLOTACION DE OTROS BIENES DE DOMINIO PÚBLICO",
    "CAPÍTULO CUARTO DE LOS CEMENTERIOS DE DOMINIO PÚBLICO",
    "CAPÍTULO QUINTO DE LAS LICENCIAS, PERMISOS Y REGISTROS",
    "CAPÍTULO SEXTO DE LAS LICENCIAS Y PERMISOS PARA ANUNCIOS",
    "CAPÍTULO SÉPTIMO LICENCIAS DE CONSTRUCCIÓN, RECONSTRUCCIÓN, REPARACIÓN O DEMOLICIÓN DE OBRAS",
    "CAPÍTULO OCTAVO REGULARIZACION DE LOS REGISTROS DE OBRA",
    "CAPÍTULO NOVENO ALINEAMIENTO, DESIGNACION DE NUMERO OFICIAL E INSPECCION",
    "CAPÍTULO DÉCIMO LICENCIAS DE CAMBIO DE REGIMEN DE PROPIEDAD Y URBANIZACIÓN",
    "CAPÍTULO DÉCIMO PRIMERO SERVICIOS POR OBRA",
    "CAPÍTULO DÉCIMO SEGUNDO SERVICIOS DE SANIDAD",
    "CAPÍTULO DÉCIMO TERCERO SERVICIO DE LIMPIA, RECOLECCION, TRASLADO, TRATAMIENTO Y DISPOSICION FINAL DE RESIDUOS",
    "CAPÍTULO DÉCIMO CUARTO",
    "CAPÍTULO DÉCIMO QUINTO RASTRO",
    "CAPÍTULO DÉCIMO SEXTO REGISTRO CIVIL",
    "CAPÍTULO DÉCIMO SÉPTIMO CERTIFICACIONES",
    "CAPÍTULO DÉCIMO OCTAVO SERVICIOS DE CATASTRO",
    "CAPÍTULO DÉCIMO NOVENO DE LOS DERECHOS NO ESPECIFICADOS",
    "CAPÍTULO VIGESIMO ACCESORIOS DE LOS DERECHOS",
    "SECCIÓN PRIMERA Del uso, goce, aprovechamiento o explotación de bienes de dominio",
    "SECCIÓN SEGUNDA DE LOS CEMENTERIOS DE DOMINIO PRIVADO",
    "SECCIÓN TERCERA PRODUCTOS DIVERSOS",
    "CAPÍTULO PRIMERO APROVECHAMIENTO",
    "CAPÍTULO UNICO INGRESOS POR VENTAS DE BIENES Y SERVICIOS DE ORGANISMOS PARAMUNICIPALES",
    "CAPÍTULO PRIMERO DE LAS PARTICIPACIONES FEDERALES Y ESTATALES",
    "CAPÍTULO SEGUNDO DE LAS APORTACIONES FEDERALES",
    "CAPÍTULO UNICO DE LAS TRANSFERENCIAS, ASIGNACIONES, SUBSIDIOS Y OTRAS AYUDAS",
    "CAPÍTULO PRIMERO FINANCIAMIENTOS INTERNOS"
  ],
  "chapter_kind_breakdown": {
    "CAPÍTULO": 34,
    "SECCIÓN": 3
  }
}